cheeru_adk/__init__.py
cheeru_adk/__main__.py
cheeru_adk/cli/__init__.py
cheeru_adk/cli/main.py
cheeru_adk/core/__init__.py
cheeru_adk/core/dispatcher.py
cheeru_adk/core/exceptions.py
cheeru_adk/core/plan.py
cheeru_adk/core/portfolio.py
cheeru_adk/core/project.py
cheeru_adk/core/spec.py
cheeru_adk/core/state.py
cheeru_adk/core/sync.py
cheeru_adk/core/task.py
cheeru_adk/core/tdd.py
cheeru_adk/core/worktree.py
cheeru_adk/integrations/__init__.py
cheeru_adk/integrations/github.py
cheeru_adk/templates/AGENTS.md
cheeru_adk/templates/.agent/agents/backend-dev.md
cheeru_adk/templates/.agent/agents/code-generator.md
cheeru_adk/templates/.agent/agents/code-reviewer.md
cheeru_adk/templates/.agent/agents/devops-engineer.md
cheeru_adk/templates/.agent/agents/frontend-dev.md
cheeru_adk/templates/.agent/agents/project-planner.md
cheeru_adk/templates/.agent/agents/technical-writer.md
cheeru_adk/templates/.agent/agents/test-engineer.md
cheeru_adk/templates/.agent/workflows/cheeru-code.md
cheeru_adk/templates/.agent/workflows/cheeru-commit.md
cheeru_adk/templates/.agent/workflows/cheeru-doc.md
cheeru_adk/templates/.agent/workflows/cheeru-issue.md
cheeru_adk/templates/.agent/workflows/cheeru-plan.md
cheeru_adk/templates/.agent/workflows/cheeru-resume.md
cheeru_adk/templates/.agent/workflows/cheeru-start.md
cheeru_adk/templates/.gemini/settings.json
cheeru_adk/templates/.gemini/commands/cheeru-1-plan.toml
cheeru_adk/templates/.gemini/commands/cheeru-2-run.toml
cheeru_adk/templates/.gemini/commands/cheeru-3-sync.toml
cheeru_adk/templates/.gemini/commands/cheeru-code.toml
cheeru_adk/templates/.gemini/commands/cheeru-commit.toml
cheeru_adk/templates/.gemini/commands/cheeru-doc.toml
cheeru_adk/templates/.gemini/commands/cheeru-issue.toml
cheeru_adk/templates/.gemini/commands/cheeru-plan.toml
cheeru_adk/templates/.gemini/commands/cheeru-resume.toml
cheeru_adk/templates/.gemini/commands/cheeru-start.toml
cheeru_adk/templates/.gemini/hooks/code-validator.sh
cheeru_adk-0.0.7.dist-info/METADATA
cheeru_adk-0.0.7.dist-info/WHEEL
cheeru_adk-0.0.7.dist-info/entry_points.txt
cheeru_adk-0.0.7.dist-info/licenses/LICENSE
cheeru_adk-0.0.7.dist-info/RECORD
