Metadata-Version: 2.4
Name: cheeru-adk
Version: 0.0.7
Summary: CheerU-ADK: AI Portfolio Auto-Generation Framework for Job Seekers (Gemini CLI)
Project-URL: Homepage, https://github.com/Dalgoi/cheeru-adk
Project-URL: Repository, https://github.com/Dalgoi/cheeru-adk
Project-URL: Issues, https://github.com/Dalgoi/cheeru-adk/issues
Project-URL: Changelog, https://github.com/Dalgoi/cheeru-adk/blob/main/CHANGELOG.md
Author-email: CheerU Team <cheeru.adk@gmail.com>
License: MIT
License-File: LICENSE
Keywords: adk,agentic,ai,automation,career,cli,gemini,job-seeker,multi-agent,portfolio,resume,spec-first,tdd
Classifier: Development Status :: 3 - Alpha
Classifier: Intended Audience :: Developers
Classifier: Intended Audience :: End Users/Desktop
Classifier: License :: OSI Approved :: MIT License
Classifier: Programming Language :: Python :: 3
Classifier: Programming Language :: Python :: 3.10
Classifier: Programming Language :: Python :: 3.11
Classifier: Programming Language :: Python :: 3.12
Classifier: Programming Language :: Python :: 3.13
Classifier: Topic :: Software Development :: Code Generators
Classifier: Topic :: Software Development :: Libraries :: Python Modules
Classifier: Topic :: Software Development :: Testing
Requires-Python: >=3.10
Requires-Dist: click>=8.0
Requires-Dist: pyyaml>=6.0
Requires-Dist: questionary>=2.0.0
Requires-Dist: rich>=13.0
Provides-Extra: dev
Requires-Dist: mypy>=1.0.0; extra == 'dev'
Requires-Dist: pytest-cov>=4.0; extra == 'dev'
Requires-Dist: pytest>=7.0; extra == 'dev'
Requires-Dist: ruff>=0.1.0; extra == 'dev'
